scanamabob/__init__.py
scanamabob/context.py
scanamabob/commands/__init__.py
scanamabob/commands/s3audit.py
scanamabob/commands/scan.py
scanamabob/commands/summary.py
scanamabob/scans/__init__.py
scanamabob/scans/cloudtrail.py
scanamabob/scans/ec2.py
scanamabob/scans/elb.py
scanamabob/scans/iam.py
scanamabob/scans/rds.py
scanamabob/scans/redshift.py
scanamabob/scans/s3.py
scanamabob/services/__init__.py
scanamabob/services/cloudtrail.py
scanamabob/services/ec2.py
scanamabob/services/elb.py
scanamabob/services/iam.py
scanamabob/services/rds.py
scanamabob/services/redshift.py
scanamabob/services/s3.py
scanamabob/services/sts.py
scanamabob-0.0.2.data/scripts/scanamabob
tests/__init__.py
tests/context.py
tests/test_s3.py
scanamabob-0.0.2.dist-info/LICENSE.txt
scanamabob-0.0.2.dist-info/METADATA
scanamabob-0.0.2.dist-info/WHEEL
scanamabob-0.0.2.dist-info/top_level.txt
scanamabob-0.0.2.dist-info/RECORD
